wagtail_form_mixins/base/blocks.py
wagtail_form_mixins/base/forms.py
wagtail_form_mixins/base/models.py
wagtail_form_mixins/blocks.py
wagtail_form_mixins/conditional_fields/__init__.py
wagtail_form_mixins/conditional_fields/blocks.py
wagtail_form_mixins/conditional_fields/hooks.py
wagtail_form_mixins/conditional_fields/models.py
wagtail_form_mixins/datepickers/forms.py
wagtail_form_mixins/emails/__init__.py
wagtail_form_mixins/emails/blocks.py
wagtail_form_mixins/emails/hooks.py
wagtail_form_mixins/emails/models.py
wagtail_form_mixins/file_input/blocks.py
wagtail_form_mixins/file_input/forms.py
wagtail_form_mixins/file_input/models.py
wagtail_form_mixins/file_input/views.py
wagtail_form_mixins/forms.py
wagtail_form_mixins/hooks.py
wagtail_form_mixins/indexed_results/models.py
wagtail_form_mixins/locale/en/LC_MESSAGES/django.mo
wagtail_form_mixins/locale/en/LC_MESSAGES/django.po
wagtail_form_mixins/locale/fr/LC_MESSAGES/django.mo
wagtail_form_mixins/locale/fr/LC_MESSAGES/django.po
wagtail_form_mixins/models.py
wagtail_form_mixins/named_form/models.py
wagtail_form_mixins/named_form/panels.py
wagtail_form_mixins/named_form/views.py
wagtail_form_mixins/nav_buttons/hooks.py
wagtail_form_mixins/nav_buttons/models.py
wagtail_form_mixins/nav_buttons/views.py
wagtail_form_mixins/panels.py
wagtail_form_mixins/static/wagtail_form_mixins/conditional_fields/css/form_admin.css
wagtail_form_mixins/static/wagtail_form_mixins/conditional_fields/js/form.js
wagtail_form_mixins/static/wagtail_form_mixins/conditional_fields/js/form_admin.js
wagtail_form_mixins/static/wagtail_form_mixins/emails/css/form_admin.css
wagtail_form_mixins/static/wagtail_form_mixins/nav_buttons/css/form_admin.css
wagtail_form_mixins/static/wagtail_form_mixins/templating/css/form_admin.css
wagtail_form_mixins/streamfield/__init__.py
wagtail_form_mixins/streamfield/blocks.py
wagtail_form_mixins/streamfield/forms.py
wagtail_form_mixins/streamfield/models.py
wagtail_form_mixins-0.4.1.dist-info/LICENSE
wagtail_form_mixins-0.4.1.dist-info/METADATA
wagtail_form_mixins-0.4.1.dist-info/WHEEL
wagtail_form_mixins-0.4.1.dist-info/RECORD
