Metadata-Version: 2.1
Name: wagtail_form_mixins
Version: 0.4.1
Summary: A set of mixins used to customise and improve Wagtail forms in a modular way.
Home-page: https://github.com/laas/wagtail-form-mixins
License: BSD-3-Clause
Keywords: wagtail,forms,plugins
Author: Nathanaël Jourdane
Author-email: njourdane@laas.fr
Requires-Python: >=3.10,<4.0
Classifier: Framework :: Wagtail
Classifier: License :: OSI Approved :: BSD License
Classifier: Programming Language :: Python :: 3
Classifier: Programming Language :: Python :: 3.10
Classifier: Programming Language :: Python :: 3.11
Classifier: Programming Language :: Python :: 3.12
Classifier: Programming Language :: Python :: 3.13
Requires-Dist: django (>=5,<6)
Requires-Dist: wagtail (>=6,<7)
Project-URL: Repository, https://github.com/laas/wagtail-form-mixins
